rusty_results/__init__.py
rusty_results/result.py
jevgeni_tarassov_rusty_results-1.0.3.dist-info/LICENSE
jevgeni_tarassov_rusty_results-1.0.3.dist-info/METADATA
jevgeni_tarassov_rusty_results-1.0.3.dist-info/WHEEL
jevgeni_tarassov_rusty_results-1.0.3.dist-info/RECORD
