Metadata-Version: 2.1
Name: jevgeni-tarassov-rusty-results
Version: 1.0.3
Summary: Result class similar to Rust's Result
Home-page: https://jevgeni.tarassov.ch/code/rusty-results
Author: Jevgeni Tarassov
Author-email: jevgeni@tarassov.ch
Requires-Python: >=3.10,<4.0
Classifier: Programming Language :: Python :: 3
Classifier: Programming Language :: Python :: 3.10
Classifier: Programming Language :: Python :: 3.11
Project-URL: Repository, https://github.com/tarassov-ch/rusty-results
